<Properties StartupConfiguration="{39262EAB-36B9-4733-8E42-888233EB7D20}|Default">
  <MonoDevelop.Ide.Workbench ActiveDocument="SadRogue/GameLoop.cs">
    <Files>
      <File FileName="SadRogue/GameLoop.cs" Line="79" Column="69" />
      <File FileName="SadRogue/TileBase.cs" Line="6" Column="2" />
      <File FileName="SadRogue/TileWall.cs" Line="7" Column="37" />
      <File FileName="SadRogue/TileFloor.cs" Line="11" Column="46" />
      <File FileName="SadRogue/Actor.cs" Line="38" Column="1" />
      <File FileName="SadRogue/Player.cs" Line="16" Column="2" />
    </Files>
  </MonoDevelop.Ide.Workbench>
  <MonoDevelop.Ide.DebuggingService.PinnedWatches />
  <MonoDevelop.Ide.ItemProperties.SadRogue PreferredExecutionTarget="MonoDevelop.Default" />
  <MonoDevelop.Ide.Workspace ActiveConfiguration="Debug" />
  <MonoDevelop.Ide.DebuggingService.Breakpoints>
    <BreakpointStore />
  </MonoDevelop.Ide.DebuggingService.Breakpoints>
  <MultiItemStartupConfigurations />
</Properties>